goldenverba/__init__.py
goldenverba/verba_manager.py
goldenverba/components/__init__.py
goldenverba/components/chunk.py
goldenverba/components/component.py
goldenverba/components/document.py
goldenverba/components/interfaces.py
goldenverba/components/managers.py
goldenverba/components/types.py
goldenverba/components/util.py
goldenverba/components/chunking/CodeChunker.py
goldenverba/components/chunking/HTMLChunker.py
goldenverba/components/chunking/JSONChunker.py
goldenverba/components/chunking/MarkdownChunker.py
goldenverba/components/chunking/RecursiveChunker.py
goldenverba/components/chunking/SemanticChunker.py
goldenverba/components/chunking/SentenceChunker.py
goldenverba/components/chunking/TokenChunker.py
goldenverba/components/chunking/__init__.py
goldenverba/components/chunking/chunk.py
goldenverba/components/chunking/chunking_examples.py
goldenverba/components/chunking/interface.py
goldenverba/components/chunking/manager.py
goldenverba/components/chunking/tiktokenchunker.py
goldenverba/components/embedding/ADAEmbedder.py
goldenverba/components/embedding/AllMPNetEmbedder.py
goldenverba/components/embedding/CohereEmbedder.py
goldenverba/components/embedding/GoogleEmbedder.py
goldenverba/components/embedding/MiniLMEmbedder.py
goldenverba/components/embedding/MixedbreadEmbedder.py
goldenverba/components/embedding/OllamaEmbedder.py
goldenverba/components/embedding/OpenAIEmbedder.py
goldenverba/components/embedding/SentenceTransformersEmbedder.py
goldenverba/components/embedding/UpstageEmbedder.py
goldenverba/components/embedding/VoyageAIEmbedder.py
goldenverba/components/embedding/WeaviateEmbedder.py
goldenverba/components/embedding/__init__.py
goldenverba/components/embedding/interface.py
goldenverba/components/embedding/manager.py
goldenverba/components/generation/AnthrophicGenerator.py
goldenverba/components/generation/CohereGenerator.py
goldenverba/components/generation/GPT3Generator.py
goldenverba/components/generation/GPT4Generator.py
goldenverba-2.1.3.dist-info/LICENSE
goldenverba-2.1.3.dist-info/METADATA
goldenverba-2.1.3.dist-info/WHEEL
goldenverba-2.1.3.dist-info/entry_points.txt
goldenverba-2.1.3.dist-info/top_level.txt
goldenverba-2.1.3.dist-info/RECORD
