Metadata-Version: 2.1
Name: goldenverba
Version: 2.1.3
Summary: Welcome to Verba: The Golden RAGtriever, an open-source initiative designed to offer a streamlined, user-friendly interface for Retrieval-Augmented Generation (RAG) applications. In just a few easy steps, dive into your data and make meaningful interactions!
Home-page: https://github.com/weaviate/Verba
Author: Weaviate
Author-email: edward@weaviate.io
Classifier: License :: OSI Approved :: BSD License
Classifier: Programming Language :: Python :: 3.10
Classifier: Programming Language :: Python :: 3.11
Classifier: Programming Language :: Python :: 3.12
Requires-Python: >=3.10.0,<3.13.0
License-File: LICENSE
Requires-Dist: weaviate-client ==4.9.6
Requires-Dist: python-dotenv ==1.0.0
Requires-Dist: openpyxl ==3.1.5
Requires-Dist: wasabi ==1.1.2
Requires-Dist: fastapi ==0.111.1
Requires-Dist: uvicorn[standard] ==0.29.0
Requires-Dist: gunicorn ==22.0.0
Requires-Dist: click ==8.1.7
Requires-Dist: xlrd ==2.0.2
Requires-Dist: asyncio ==3.4.3
Requires-Dist: tiktoken ==0.6.0
Requires-Dist: requests ==2.31.0
Requires-Dist: pypdf ==4.3.1
Requires-Dist: python-docx ==1.1.2
Requires-Dist: scikit-learn ==1.5.1
Requires-Dist: langchain-text-splitters ==0.2.2
Requires-Dist: spacy ==3.7.5
Requires-Dist: aiohttp ==3.9.5
Requires-Dist: markdownify ==0.13.1
Requires-Dist: aiofiles ==24.1.0
Requires-Dist: assemblyai ==0.33.0
Requires-Dist: beautifulsoup4 ==4.12.3
Requires-Dist: langdetect ==1.0.9
Provides-Extra: dev
Requires-Dist: pytest ; extra == 'dev'
Requires-Dist: wheel ; extra == 'dev'
Requires-Dist: twine ; extra == 'dev'
Requires-Dist: black >=23.7.0 ; extra == 'dev'
Requires-Dist: setuptools ; extra == 'dev'
Provides-Extra: google
Requires-Dist: vertexai ==1.46.0 ; extra == 'google'
Provides-Extra: huggingface
Requires-Dist: sentence-transformers ==3.0.1 ; extra == 'huggingface'
